{"success":true,"source":"xp2cvs.pl","last_updated":"2013/03/06 18:03:30 UTC"
,"icao":"KMFE","name":"Mc Allen Miller Intl","lat":26.17624375,"lon":-98.237896,"rwys":2,"ils":1
,"runways":[
{"len_m":2170,"wid_m":46.02,"hdg":140,"surf":"Asphalt","rwy1":"13","lat1":26.18292800,"lon1":-098.24632800,"rwy2":"31","lat2":26.16779700,"lon2":-098.23254200},
{"len_m":803,"wid_m":17.98,"hdg":188,"surf":"Asphalt","rwy1":"18","lat1":26.18071100,"lon1":-098.23574700,"rwy2":"36","lat2":26.17353900,"lon2":-098.23696700}
]
,"radios":[
{"type":"ATIS","freq":128.5,"desc":"ASOS"},
{"type":"CTAF","freq":118.5,"desc":"CTAF"},
{"type":"CTAF","freq":122.95,"desc":"UNICOM"},
{"type":"GND","freq":121.8,"desc":"GND"},
{"type":"TWR","freq":118.5,"desc":"TWR"},
{"type":"APP","freq":121,"desc":"VALLEY APP/DEP"}
]
}
