{"success":true,"source":"xp2cvs.pl","last_updated":"2013/03/06 18:03:30 UTC"
,"icao":"RKNY","name":"Yangyang Intl","lat":38.06131,"lon":128.669161,"rwys":1,"ils":1
,"runways":[
{"len_m":2499,"wid_m":45.11,"hdg":140,"surf":"Asphalt","rwy1":"15","lat1":38.07005600,"lon1":128.66018900,"rwy2":"33","lat2":38.05256400,"lon2":128.67813300}
]
,"radios":[
{"type":"CLD","freq":123.15,"desc":"CLD"},
{"type":"GND","freq":123.15,"desc":"GND"},
{"type":"TWR","freq":130.8,"desc":"TWR"},
{"type":"TWR","freq":123.15,"desc":"TWR"},
{"type":"TWR","freq":118.85,"desc":"TWR"},
{"type":"APP","freq":124.6,"desc":"GANGNEUNG APP"},
{"type":"DEP","freq":124.6,"desc":"GANGNEUNG DEP"}
]
}
