{"success":true,"source":"xp2csv.pl","last_updated":"2013/03/09 16:54:19 UTC"
,"icao":"EGUL","name":"Raf Lakenheath","lat":52.409407,"lon":0.56101762,"rwys":1,"ils":2,"index":2958234,"path":"e000n50/e000n52"
,"runways":[
{"len_m":2740,"wid_m":46.02,"hdg":55,"surf":"Asphalt","rwy1":"06","lat1":52.40246056,"lon1":0.54438686,"rwy2":"24","lat2":52.41635344,"lon2":0.57764838}
]
,"radios":[
{"type":"TWR","freq":122.1,"desc":"Lakenheath Tower"},
{"type":"APP","freq":136.5,"desc":"Lakenheath Approach"},
{"type":"APP","freq":128.9,"desc":"Lakenheath Radar"}
]
,"ils":[
{"type":"ILS","freq":109.9,"lat":52.41817500,"lon":0.58206100,"rng_nm":18,"alt_fmsl":28,"hdg":55.65,"id":"ILAK","rwy":"06","desc":"ILS-cat-I"},
{"type":"ILS","freq":109.9,"lat":52.40080000,"lon":0.53483900,"rng_nm":18,"alt_fmsl":23,"hdg":239.21,"id":"ILKH","rwy":"24","desc":"ILS-cat-I"},
{"type":"GS","freq":109.9,"lat":52.40306900,"lon":0.54900800,"rng_nm":10,"alt_fmsl":31,"id":"ILAK","rwy":"06","desc":"GS","gs":2.5},
{"type":"GS","freq":109.9,"lat":52.41541900,"lon":0.57267800,"rng_nm":10,"alt_fmsl":28,"id":"ILKH","rwy":"24","desc":"GS","gs":2.5}
]
,"navaids":[
{"type":"SDME","hdg_t":249.4,"dist_nm":0.5,"freq":110.2,"lat":52.40641900,"lon":0.54796400,"rng_nm":25,"alt_fmsl":91,"id":"LKH","desc":"LAKENHEATH TACAN"},
{"type":"SDME","hdg_t":224,"dist_nm":3.8,"freq":115.9,"lat":52.36335000,"lon":0.48826900,"rng_nm":130,"alt_fmsl":63,"id":"MLD","desc":"MILDENHALL TACAN"},
{"type":"SDME","hdg_t":358.8,"dist_nm":14.2,"freq":108.7,"lat":52.64726100,"lon":0.55326400,"rng_nm":25,"alt_fmsl":75,"id":"MAM","desc":"MARHAM TACAN"},
{"type":"NDB","hdg_t":229.5,"dist_nm":18.3,"freq":332,"lat":52.21085000,"lon":0.18279200,"rng_nm":15,"alt_fmsl":0,"id":"CAM","desc":"CAMBRIDGE NDB"},
{"type":"NDB","hdg_t":46.1,"dist_nm":18.5,"freq":348,"lat":52.62305500,"lon":0.92694400,"rng_nm":150,"alt_fmsl":0,"id":"SDM","desc":"SHIPDHAM NDB"},
{"type":"SDME","hdg_t":140.8,"dist_nm":22.2,"freq":109.3,"lat":52.12193300,"lon":0.94046900,"rng_nm":130,"alt_fmsl":324,"id":"WTZ","desc":"WATTISHAM TACAN"},
{"type":"NDB","hdg_t":242.1,"dist_nm":25.2,"freq":391,"lat":52.21113600,"lon":-0.04493600,"rng_nm":15,"alt_fmsl":0,"id":"BOU","desc":"BOURN NDB"},
{"type":"NDB","hdg_t":53.9,"dist_nm":27.1,"freq":342,"lat":52.67416800,"lon":1.16222200,"rng_nm":150,"alt_fmsl":0,"id":"DH","desc":"NORWICH NDB"},
{"type":"NDB","hdg_t":313,"dist_nm":29.3,"freq":401,"lat":52.74165000,"lon":-0.02794200,"rng_nm":15,"alt_fmsl":0,"id":"FNL","desc":"FENLAND NDB"},
{"type":"VOR","hdg_t":216.3,"dist_nm":31.2,"freq":116.25,"lat":51.98972200,"lon":0.06194400,"rng_nm":40,"alt_fmsl":486,"id":"BKY","desc":"BARKWAY VOR-DME"},
{"type":"NDB","hdg_t":133.7,"dist_nm":32.8,"freq":328,"lat":52.02888900,"lon":1.20138900,"rng_nm":150,"alt_fmsl":0,"id":"PSW","desc":"IPSWICH NDB"},
{"type":"NDB","hdg_t":200.8,"dist_nm":33,"freq":429,"lat":51.89459200,"lon":0.24503100,"rng_nm":20,"alt_fmsl":0,"id":"SSD","desc":"STANSTED NDB"},
{"type":"NDB","hdg_t":61.6,"dist_nm":34.1,"freq":371,"lat":52.67642200,"lon":1.38471100,"rng_nm":20,"alt_fmsl":0,"id":"NL","desc":"NORWICH NDB"},
{"type":"VOR","hdg_t":147,"dist_nm":40,"freq":114.55,"lat":51.84841700,"lon":1.14761100,"rng_nm":100,"alt_fmsl":100,"id":"CLN","desc":"CLACTON VOR-DME"},
{"type":"NDB","hdg_t":146.9,"dist_nm":40.1,"freq":295,"lat":51.84805700,"lon":1.14944400,"rng_nm":150,"alt_fmsl":0,"id":"CLN","desc":"CLACTON NDB"},
{"type":"SDME","hdg_t":287.4,"dist_nm":40.6,"freq":117.6,"lat":52.60783300,"lon":-0.49866700,"rng_nm":25,"alt_fmsl":295,"id":"WIT","desc":"WITTERING TACAN"},
{"type":"NDB","hdg_t":224.4,"dist_nm":43.1,"freq":345,"lat":51.89416800,"lon":-0.25083300,"rng_nm":50,"alt_fmsl":0,"id":"LUT","desc":"Luton NDB"},
{"type":"NDB","hdg_t":248.3,"dist_nm":44.4,"freq":850,"lat":52.13033300,"lon":-0.55700000,"rng_nm":50,"alt_fmsl":364,"id":"CIT","desc":"Cranfield NDB"},
{"type":"NDB","hdg_t":71.7,"dist_nm":44.8,"freq":397,"lat":52.63694400,"lon":1.72527800,"rng_nm":150,"alt_fmsl":0,"id":"ND","desc":"GREAT YARMOUTH NDB"},
{"type":"VOR","hdg_t":212.2,"dist_nm":46.7,"freq":117.5,"lat":51.74972200,"lon":-0.10666700,"rng_nm":80,"alt_fmsl":382,"id":"BPK","desc":"BROOKMANS PARK VOR-DME"},
{"type":"VOR","hdg_t":245.4,"dist_nm":47.6,"freq":116.5,"lat":52.07421700,"lon":-0.61079200,"rng_nm":50,"alt_fmsl":357,"id":"CFD","desc":"CRANFIELD VOR"},
{"type":"VOR","hdg_t":198.4,"dist_nm":48.3,"freq":115.6,"lat":51.64611100,"lon":0.15166700,"rng_nm":110,"alt_fmsl":200,"id":"LAM","desc":"LAMBOURNE VOR-DME"},
{"type":"SDME","hdg_t":294.3,"dist_nm":48.4,"freq":112.3,"lat":52.73537800,"lon":-0.65076900,"rng_nm":25,"alt_fmsl":452,"id":"CTM","desc":"COTTESMORE TACAN"},
{"type":"SDME","hdg_t":327.2,"dist_nm":48.8,"freq":111.1,"lat":53.09103900,"lon":-0.16897500,"rng_nm":120,"alt_fmsl":24,"id":"CGY","desc":"CONINGSBY TACAN"},
{"type":"NDB","hdg_t":174,"dist_nm":50.3,"freq":362,"lat":51.57632800,"lon":0.70033000,"rng_nm":50,"alt_fmsl":50,"id":"SND","desc":"Southend NDB"},
{"type":"NDB","hdg_t":262.9,"dist_nm":50.4,"freq":378,"lat":52.29909200,"lon":-0.79760300,"rng_nm":15,"alt_fmsl":0,"id":"NN","desc":"NORTHAMPTON NDB"},
{"type":"NDB","hdg_t":314.4,"dist_nm":53.3,"freq":423,"lat":53.02627800,"lon":-0.48898300,"rng_nm":25,"alt_fmsl":0,"id":"CWL","desc":"CRANWELL NDB"},
{"type":"SDME","hdg_t":314.6,"dist_nm":53.3,"freq":117.4,"lat":53.02861700,"lon":-0.48550000,"rng_nm":65,"alt_fmsl":218,"id":"CWZ","desc":"CRANWELL TACAN"},
{"type":"NDB","hdg_t":345.6,"dist_nm":55.8,"freq":330,"lat":53.31000000,"lon":0.17616700,"rng_nm":25,"alt_fmsl":0,"id":"SBY","desc":"STRUBBY NDB"},
{"type":"NDB","hdg_t":198.8,"dist_nm":57.3,"freq":322,"lat":51.50435000,"lon":0.06750300,"rng_nm":10,"alt_fmsl":0,"id":"LCY","desc":"CITY NDB"},
{"type":"VOR","hdg_t":225.4,"dist_nm":58.1,"freq":113.75,"lat":51.72611100,"lon":-0.54972200,"rng_nm":130,"alt_fmsl":500,"id":"BNN","desc":"BOVINGDON VOR-DME"},
{"type":"NDB","hdg_t":282,"dist_nm":59.6,"freq":383,"lat":52.60638900,"lon":-1.03500000,"rng_nm":10,"alt_fmsl":0,"id":"LE","desc":"LEICESTER NDB"},
{"type":"SDME","hdg_t":319.3,"dist_nm":60.2,"freq":117.1,"lat":53.16533300,"lon":-0.52683300,"rng_nm":130,"alt_fmsl":231,"id":"WAD","desc":"WADDINGTON TACAN"},
{"type":"NDB","hdg_t":220.6,"dist_nm":61.9,"freq":277,"lat":51.62305600,"lon":-0.51833300,"rng_nm":25,"alt_fmsl":0,"id":"CHT","desc":"CHILTERN NDB"},
{"type":"VOR","hdg_t":258,"dist_nm":63.2,"freq":116.4,"lat":52.18027800,"lon":-1.11388900,"rng_nm":130,"alt_fmsl":600,"id":"DTY","desc":"DAVENTRY VOR-DME"},
{"type":"NDB","hdg_t":232.5,"dist_nm":63.4,"freq":433,"lat":51.75972200,"lon":-0.79027800,"rng_nm":30,"alt_fmsl":0,"id":"HEN","desc":"HENTON NDB"},
{"type":"NDB","hdg_t":181.9,"dist_nm":63.4,"freq":369,"lat":51.35383300,"lon":0.50366700,"rng_nm":25,"alt_fmsl":0,"id":"RCH","desc":"ROCHESTER NDB"},
{"type":"NDB","hdg_t":239.9,"dist_nm":65.5,"freq":335,"lat":51.85305600,"lon":-0.96250000,"rng_nm":30,"alt_fmsl":0,"id":"WCO","desc":"WESTCOTT NDB"},
{"type":"VOR","hdg_t":178.8,"dist_nm":66.4,"freq":117.3,"lat":51.30388900,"lon":0.59722200,"rng_nm":130,"alt_fmsl":645,"id":"DET","desc":"DETLING VOR-DME"},
{"type":"VOR","hdg_t":214.9,"dist_nm":67.2,"freq":113.6,"lat":51.48722200,"lon":-0.46666700,"rng_nm":130,"alt_fmsl":110,"id":"LON","desc":"LONDON VOR-DME"},
{"type":"NDB","hdg_t":297.8,"dist_nm":67.3,"freq":430,"lat":52.92169400,"lon":-1.07933300,"rng_nm":10,"alt_fmsl":0,"id":"NOT","desc":"NOTTINGHAM NDB"},
{"type":"VOR","hdg_t":197,"dist_nm":67.6,"freq":115.1,"lat":51.33087500,"lon":0.03481100,"rng_nm":125,"alt_fmsl":590,"id":"BIG","desc":"BIGGIN VOR-DME"},
{"type":"NDB","hdg_t":292.3,"dist_nm":69,"freq":353,"lat":52.83283300,"lon":-1.19450000,"rng_nm":50,"alt_fmsl":280,"id":"EME","desc":"East Midlands NDB"},
{"type":"NDB","hdg_t":151.7,"dist_nm":70.3,"freq":301,"lat":51.37444300,"lon":1.44666700,"rng_nm":50,"alt_fmsl":0,"id":"NF","desc":"NORTH FORELAND NDB"},
{"type":"NDB","hdg_t":221.1,"dist_nm":70.5,"freq":421,"lat":51.51888900,"lon":-0.67722200,"rng_nm":30,"alt_fmsl":0,"id":"BUR","desc":"BURNHAM NDB"},
{"type":"NDB","hdg_t":270.8,"dist_nm":72.2,"freq":363,"lat":52.41100000,"lon":-1.40583300,"rng_nm":50,"alt_fmsl":360,"id":"CT","desc":"Coventry NDB"},
{"type":"NDB","hdg_t":208.2,"dist_nm":74.1,"freq":316,"lat":51.31944400,"lon":-0.37194400,"rng_nm":25,"alt_fmsl":0,"id":"EPM","desc":"EPSOM NDB"},
{"type":"NDB","hdg_t":177.5,"dist_nm":75.4,"freq":340,"lat":51.15472200,"lon":0.64805600,"rng_nm":15,"alt_fmsl":72,"id":"LSH","desc":"LASHENDEN NDB-DME"},
{"type":"SDME","hdg_t":177.5,"dist_nm":75.4,"freq":115.95,"lat":51.15472200,"lon":0.64805600,"rng_nm":15,"alt_fmsl":72,"id":"LSH","desc":"LASHENDEN NDB-DME"},
{"type":"VOR","hdg_t":314.2,"dist_nm":75.8,"freq":112.8,"lat":53.28138900,"lon":-0.94722200,"rng_nm":130,"alt_fmsl":121,"id":"GAM","desc":"GAMSTON VOR-DME"},
{"type":"VOR","hdg_t":209.8,"dist_nm":76.2,"freq":115.3,"lat":51.30500000,"lon":-0.44722200,"rng_nm":70,"alt_fmsl":200,"id":"OCK","desc":"OCKHAM VOR-DME"},
{"type":"NDB","hdg_t":213.7,"dist_nm":76.3,"freq":348,"lat":51.34741100,"lon":-0.56542900,"rng_nm":10,"alt_fmsl":80,"id":"FOS","desc":"FAIROAKS NDB"},
{"type":"NDB","hdg_t":200.2,"dist_nm":76.3,"freq":343,"lat":51.21494400,"lon":-0.13925000,"rng_nm":10,"alt_fmsl":0,"id":"RDL","desc":"REDHILL NDB"},
{"type":"SDME","hdg_t":213.7,"dist_nm":76.3,"freq":109.85,"lat":51.34741100,"lon":-0.56542900,"rng_nm":8,"alt_fmsl":80,"id":"FRK","desc":"FAIROAKS DME"},
{"type":"NDB","hdg_t":335.1,"dist_nm":77.5,"freq":365,"lat":53.57666700,"lon":-0.35166700,"rng_nm":15,"alt_fmsl":0,"id":"KIM","desc":"HUMBERSIDE NDB"},
{"type":"NDB","hdg_t":289.6,"dist_nm":77.8,"freq":393,"lat":52.82866600,"lon":-1.45450000,"rng_nm":50,"alt_fmsl":280,"id":"EMW","desc":"East Midlands NDB"},
{"type":"NDB","hdg_t":244.2,"dist_nm":77.8,"freq":367,"lat":51.83248100,"lon":-1.32323900,"rng_nm":25,"alt_fmsl":0,"id":"OX","desc":"OXFORD NDB"},
{"type":"SDME","hdg_t":244.2,"dist_nm":77.8,"freq":117.7,"lat":51.83243300,"lon":-1.32281700,"rng_nm":25,"alt_fmsl":276,"id":"OX","desc":"OXFORD DME"},
{"type":"SDME","hdg_t":232.8,"dist_nm":77.9,"freq":110,"lat":51.61450000,"lon":-1.09944400,"rng_nm":40,"alt_fmsl":226,"id":"BSO","desc":"BENSON TACAN"},
{"type":"NDB","hdg_t":197.6,"dist_nm":78.3,"freq":338,"lat":51.16443900,"lon":-0.06913300,"rng_nm":15,"alt_fmsl":0,"id":"GE","desc":"GATWICK NDB"},
{"type":"NDB","hdg_t":223.5,"dist_nm":78.5,"freq":352,"lat":51.45277800,"lon":-0.87888900,"rng_nm":25,"alt_fmsl":0,"id":"WOD","desc":"WOODLEY NDB"},
{"type":"VOR","hdg_t":158,"dist_nm":80.5,"freq":114.95,"lat":51.16250000,"lon":1.35916700,"rng_nm":130,"alt_fmsl":315,"id":"DVR","desc":"DOVER VOR-DME"},
{"type":"VOR","hdg_t":343,"dist_nm":81.1,"freq":113.9,"lat":53.69833300,"lon":-0.10361100,"rng_nm":100,"alt_fmsl":0,"id":"OTR","desc":"OTTRINGHAM VOR-DME"},
{"type":"VOR","hdg_t":268.6,"dist_nm":81.8,"freq":113.65,"lat":52.35666700,"lon":-1.66361100,"rng_nm":130,"alt_fmsl":435,"id":"HON","desc":"HONILEY VOR-DME"},
{"type":"NDB","hdg_t":203.3,"dist_nm":83.4,"freq":365,"lat":51.13065300,"lon":-0.31595600,"rng_nm":15,"alt_fmsl":0,"id":"GY","desc":"GATWICK NDB"},
{"type":"NDB","hdg_t":219.2,"dist_nm":83.6,"freq":328,"lat":51.32328900,"lon":-0.84479400,"rng_nm":15,"alt_fmsl":0,"id":"BLK","desc":"BLACKBUSHE NDB"},
{"type":"SDME","hdg_t":219.3,"dist_nm":83.6,"freq":116.2,"lat":51.32386500,"lon":-0.84637700,"rng_nm":50,"alt_fmsl":341,"id":"BLC","desc":"BLACKBUSHE DME"},
{"type":"NDB","hdg_t":272.7,"dist_nm":84.9,"freq":406,"lat":52.45454700,"lon":-1.75238600,"rng_nm":20,"alt_fmsl":325,"id":"BHX","desc":"BIRMINGHAM NDB"},
{"type":"VOR","hdg_t":191.4,"dist_nm":85.2,"freq":117.9,"lat":51.01722200,"lon":0.11611100,"rng_nm":130,"alt_fmsl":360,"id":"MAY","desc":"MAYFIELD VOR-DME"},
{"type":"NDB","hdg_t":319,"dist_nm":85.5,"freq":338,"lat":53.47482200,"lon":-1.00172500,"rng_nm":25,"alt_fmsl":0,"id":"FNY","desc":"DONCASTER NDB"},
{"type":"VOR","hdg_t":171.9,"dist_nm":85.5,"freq":114.05,"lat":50.99972200,"lon":0.87861100,"rng_nm":130,"alt_fmsl":30,"id":"LYD","desc":"LYDD VOR-DME"},
{"type":"NDB","hdg_t":284.5,"dist_nm":85.8,"freq":545,"lat":52.74666700,"lon":-1.71944400,"rng_nm":50,"alt_fmsl":0,"id":"LIC","desc":"LICHFIELD NDB"},
{"type":"VOR","hdg_t":230.8,"dist_nm":86,"freq":114.35,"lat":51.49166700,"lon":-1.21972200,"rng_nm":80,"alt_fmsl":498,"id":"CPT","desc":"COMPTON VOR-DME"},
{"type":"NDB","hdg_t":170.1,"dist_nm":87.5,"freq":397,"lat":50.97216400,"lon":0.95528600,"rng_nm":15,"alt_fmsl":0,"id":"LYX","desc":"LYDD NDB"},
{"type":"NDB","hdg_t":286.8,"dist_nm":88.5,"freq":327,"lat":52.81446400,"lon":-1.76667200,"rng_nm":10,"alt_fmsl":0,"id":"TNL","desc":"TATENHILL NDB"},
{"type":"NDB","hdg_t":332.8,"dist_nm":89.2,"freq":372,"lat":53.72538100,"lon":-0.58148300,"rng_nm":15,"alt_fmsl":12,"id":"BV","desc":"BROUGH NDB"},
{"type":"NDB","hdg_t":244.4,"dist_nm":89.3,"freq":386,"lat":51.74923300,"lon":-1.60161700,"rng_nm":20,"alt_fmsl":288,"id":"BZ","desc":"BRIZE NORTON NDB"},
{"type":"SDME","hdg_t":244.4,"dist_nm":89.4,"freq":111.9,"lat":51.74819400,"lon":-1.60352500,"rng_nm":100,"alt_fmsl":331,"id":"BZN","desc":"BRIZE NORTON TACAN"},
{"type":"VOR","hdg_t":296.3,"dist_nm":90.1,"freq":115.7,"lat":53.05388900,"lon":-1.67000000,"rng_nm":130,"alt_fmsl":968,"id":"TNT","desc":"TRENT VOR-DME"},
{"type":"SDME","hdg_t":219,"dist_nm":90.2,"freq":109.6,"lat":51.23284700,"lon":-0.94849200,"rng_nm":40,"alt_fmsl":410,"id":"ODH","desc":"ODIHAM TACAN"},
{"type":"NDB","hdg_t":310.6,"dist_nm":92,"freq":333,"lat":53.39263900,"lon":-1.38313600,"rng_nm":15,"alt_fmsl":0,"id":"SMF","desc":"SHEFFIELD CITY NDB"},
{"type":"SDME","hdg_t":310.6,"dist_nm":92,"freq":111.35,"lat":53.39298100,"lon":-1.38314200,"rng_nm":25,"alt_fmsl":273,"id":"SFH","desc":"SHEFFIELD CITY DME"},
{"type":"VOR","hdg_t":208.9,"dist_nm":92.6,"freq":114,"lat":51.05388900,"lon":-0.62500000,"rng_nm":100,"alt_fmsl":200,"id":"MID","desc":"MIDHURST VOR-DME"},
{"type":"SDME","hdg_t":244.3,"dist_nm":97.6,"freq":113.4,"lat":51.68169200,"lon":-1.79761400,"rng_nm":25,"alt_fmsl":299,"id":"FFA","desc":"FAIRFORD TACAN"},
{"type":"NDB","hdg_t":199,"dist_nm":99.8,"freq":332,"lat":50.83550000,"lon":-0.29550000,"rng_nm":10,"alt_fmsl":0,"id":"SHM","desc":"Shoreham NDB"}
]
}
