{"success":true,"source":"xp2csv.pl","last_updated":"2013/03/09 16:54:19 UTC"
,"icao":"KCXO","name":"Lone Star Executive","lat":30.35232407,"lon":-95.41476069,"rwys":2,"ils":1,"index":1383954,"path":"w100n30/w096n30"
,"runways":[
{"len_m":1828,"wid_m":46.02,"hdg":145,"surf":"Asphalt","rwy1":"14","lat1":30.35930000,"lon1":-95.41775300,"rwy2":"32","lat2":30.34570800,"lon2":-95.40697500},
{"len_m":1521,"wid_m":29.87,"hdg":17,"surf":"Asphalt","rwy1":"01","lat1":30.34558705,"lon1":-95.41948784,"rwy2":"19","lat2":30.35870122,"lon2":-95.41482693}
]
,"radios":[
{"type":"ATIS","freq":118.32,"desc":"ASOS"},
{"type":"CTAF","freq":122.95,"desc":"CTAF/UNICOM"},
{"type":"CLD","freq":119.55,"desc":"CLNC DEL"},
{"type":"APP","freq":119.7,"desc":"HOUSTON APP/DEP"}
]
,"ils":[
{"type":"ILS","freq":108.7,"lat":30.34479400,"lon":-95.40625000,"rng_nm":18,"alt_fmsl":245,"hdg":145.62,"id":"ICXO","rwy":"14","desc":"ILS-cat-I"},
{"type":"GS","freq":108.7,"lat":30.35674400,"lon":-95.41418600,"rng_nm":10,"alt_fmsl":230,"id":"ICXO","rwy":"14","desc":"GS","gs":3},
{"type":"OM","freq":0,"lat":30.43201100,"lon":-95.47624700,"rng_nm":0,"alt_fmsl":245,"id":"----","rwy":"14","desc":"OM"},
{"type":"MM","freq":0,"lat":30.36531700,"lon":-95.42252200,"rng_nm":0,"alt_fmsl":245,"id":"----","rwy":"14","desc":"MM"},
{"type":"DME","freq":108.7,"lat":30.34438300,"lon":-95.40695600,"rng_nm":18,"alt_fmsl":251,"id":"ICXO","rwy":"14","desc":"DME-ILS"}
]
,"navaids":[
{"type":"NDB","hdg_t":326.2,"dist_nm":5.7,"freq":281,"lat":30.43200000,"lon":-95.47625000,"rng_nm":50,"alt_fmsl":0,"id":"CX","desc":"ALIBI NDB"},
{"type":"NDB","hdg_t":210,"dist_nm":15.6,"freq":521,"lat":30.12552778,"lon":-95.56586111,"rng_nm":50,"alt_fmsl":0,"id":"DWH","desc":"DAVID HOOKS NDB"},
{"type":"NDB","hdg_t":154.1,"dist_nm":23.8,"freq":326,"lat":29.99333333,"lon":-95.21502778,"rng_nm":50,"alt_fmsl":0,"id":"BVP","desc":"NIXIN NDB"},
{"type":"VOR","hdg_t":171.3,"dist_nm":23.9,"freq":116.6,"lat":29.95691667,"lon":-95.34572222,"rng_nm":130,"alt_fmsl":90,"id":"IAH","desc":"HUMBLE VORTAC"},
{"type":"NDB","hdg_t":338.6,"dist_nm":24.9,"freq":308,"lat":30.74075000,"lon":-95.59086111,"rng_nm":50,"alt_fmsl":0,"id":"UTS","desc":"HUNTSVILLE NDB"},
{"type":"NDB","hdg_t":205.2,"dist_nm":27.6,"freq":286,"lat":29.93386111,"lon":-95.64100000,"rng_nm":50,"alt_fmsl":0,"id":"EYQ","desc":"WEISER NDB"},
{"type":"VOR","hdg_t":263.6,"dist_nm":33.6,"freq":115.9,"lat":30.28852778,"lon":-96.05822222,"rng_nm":130,"alt_fmsl":230,"id":"TNV","desc":"NAVASOTA VORTAC"},
{"type":"VOR","hdg_t":103.4,"dist_nm":41.1,"freq":116.9,"lat":30.18972222,"lon":-94.64497222,"rng_nm":130,"alt_fmsl":76,"id":"DAS","desc":"DAISETTA VORTAC"},
{"type":"VOR","hdg_t":170.1,"dist_nm":42.3,"freq":117.1,"lat":29.65563889,"lon":-95.27663889,"rng_nm":130,"alt_fmsl":82,"id":"HUB","desc":"HOBBY VOR-DME"},
{"type":"NDB","hdg_t":156.2,"dist_nm":44.7,"freq":347,"lat":29.66841667,"lon":-95.06983333,"rng_nm":50,"alt_fmsl":0,"id":"JPA","desc":"SANJAC NDB"},
{"type":"SDME","hdg_t":163.3,"dist_nm":46.6,"freq":109.4,"lat":29.60595800,"lon":-95.15965300,"rng_nm":40,"alt_fmsl":30,"id":"EFD","desc":"ELLINGTON TACAN"},
{"type":"NDB","hdg_t":280.2,"dist_nm":48.6,"freq":260,"lat":30.49372222,"lon":-96.33769444,"rng_nm":50,"alt_fmsl":0,"id":"CL","desc":"ROWDY NDB"},
{"type":"VOR","hdg_t":286.4,"dist_nm":54.3,"freq":113.3,"lat":30.60500000,"lon":-96.42069444,"rng_nm":40,"alt_fmsl":275,"id":"CLL","desc":"COLLEGE STATION VORTAC"},
{"type":"VOR","hdg_t":328.3,"dist_nm":54.3,"freq":110.8,"lat":31.12402778,"lon":-95.96794444,"rng_nm":40,"alt_fmsl":350,"id":"LOA","desc":"LEONA VORTAC"},
{"type":"VOR","hdg_t":144,"dist_nm":59.4,"freq":113.6,"lat":29.54633333,"lon":-94.74750000,"rng_nm":40,"alt_fmsl":38,"id":"MHF","desc":"TRINITY VOR-DME"},
{"type":"NDB","hdg_t":90.6,"dist_nm":59.9,"freq":524,"lat":30.33633333,"lon":-94.26036111,"rng_nm":50,"alt_fmsl":0,"id":"HRD","desc":"HARDIN CO NDB"},
{"type":"NDB","hdg_t":30.2,"dist_nm":60.1,"freq":350,"lat":31.21888889,"lon":-94.82508333,"rng_nm":50,"alt_fmsl":0,"id":"LF","desc":"FLUFY NDB"},
{"type":"VOR","hdg_t":36.4,"dist_nm":60.4,"freq":112.1,"lat":31.16236111,"lon":-94.71694444,"rng_nm":130,"alt_fmsl":200,"id":"LFK","desc":"LUFKIN VORTAC"},
{"type":"VOR","hdg_t":228.9,"dist_nm":62.5,"freq":116.4,"lat":29.66244444,"lon":-96.31716667,"rng_nm":130,"alt_fmsl":190,"id":"ELA","desc":"EAGLE LAKE VOR-DME"},
{"type":"VOR","hdg_t":248.6,"dist_nm":64.2,"freq":110.2,"lat":29.95605556,"lon":-96.56219444,"rng_nm":40,"alt_fmsl":419,"id":"IDU","desc":"INDUSTRY VORTAC"},
{"type":"NDB","hdg_t":104.7,"dist_nm":64.8,"freq":368,"lat":30.07047222,"lon":-94.21102778,"rng_nm":50,"alt_fmsl":0,"id":"GDE","desc":"GOODHUE NDB"},
{"type":"NDB","hdg_t":182.1,"dist_nm":69.3,"freq":263,"lat":29.19433333,"lon":-95.46316667,"rng_nm":50,"alt_fmsl":0,"id":"LB","desc":"FREEP NDB"},
{"type":"NDB","hdg_t":150.4,"dist_nm":69.9,"freq":206,"lat":29.33397222,"lon":-94.75622222,"rng_nm":75,"alt_fmsl":0,"id":"GLS","desc":"GALVESTON NDB"},
{"type":"VOR","hdg_t":156,"dist_nm":70.8,"freq":113,"lat":29.26933333,"lon":-94.86772222,"rng_nm":40,"alt_fmsl":4,"id":"VUH","desc":"SCHOLES VORTAC"},
{"type":"NDB","hdg_t":210.5,"dist_nm":76.1,"freq":245,"lat":29.25463889,"lon":-96.15202778,"rng_nm":50,"alt_fmsl":0,"id":"ARM","desc":"WHARTON NDB"},
{"type":"NDB","hdg_t":27.6,"dist_nm":76.7,"freq":253,"lat":31.48555556,"lon":-94.72019444,"rng_nm":50,"alt_fmsl":0,"id":"OC","desc":"NADOS NDB"},
{"type":"VOR","hdg_t":108.1,"dist_nm":76.7,"freq":114.5,"lat":29.94605556,"lon":-94.01622222,"rng_nm":40,"alt_fmsl":10,"id":"BPT","desc":"BEAUMONT VOR-DME"},
{"type":"NDB","hdg_t":262.7,"dist_nm":81.9,"freq":385,"lat":30.16952200,"lon":-96.97874400,"rng_nm":25,"alt_fmsl":464,"id":"GYB","desc":"LEE COUNTY NDB"},
{"type":"VOR","hdg_t":118.7,"dist_nm":82,"freq":115.4,"lat":29.68672222,"lon":-94.03797222,"rng_nm":40,"alt_fmsl":10,"id":"SBI","desc":"SABINE PASS VOR-DME"},
{"type":"NDB","hdg_t":195.8,"dist_nm":85.7,"freq":344,"lat":28.97250000,"lon":-95.85913889,"rng_nm":50,"alt_fmsl":0,"id":"BYY","desc":"BAY CITY NDB"},
{"type":"NDB","hdg_t":25,"dist_nm":85.7,"freq":391,"lat":31.64850000,"lon":-94.70550000,"rng_nm":50,"alt_fmsl":0,"id":"GXD","desc":"NACOGDOCHES NDB"},
{"type":"NDB","hdg_t":100.9,"dist_nm":85.8,"freq":211,"lat":30.07027778,"lon":-93.79494444,"rng_nm":50,"alt_fmsl":0,"id":"ORG","desc":"ORANGE NDB"},
{"type":"NDB","hdg_t":350.2,"dist_nm":86.7,"freq":375,"lat":31.78016667,"lon":-95.70105556,"rng_nm":50,"alt_fmsl":0,"id":"PSN","desc":"PALESTINE NDB"},
{"type":"NDB","hdg_t":6.3,"dist_nm":91.4,"freq":263,"lat":31.87016667,"lon":-95.21550000,"rng_nm":50,"alt_fmsl":0,"id":"JSO","desc":"CHEROKEE CO NDB"},
{"type":"VOR","hdg_t":321.7,"dist_nm":94,"freq":108.8,"lat":31.58147222,"lon":-96.54908333,"rng_nm":40,"alt_fmsl":512,"id":"GNL","desc":"GROESBECK VOR-DME"},
{"type":"NDB","hdg_t":323.9,"dist_nm":95.6,"freq":329,"lat":31.63961111,"lon":-96.51219444,"rng_nm":50,"alt_fmsl":0,"id":"LXY","desc":"MEXIA NDB"},
{"type":"NDB","hdg_t":336.1,"dist_nm":98.9,"freq":418,"lat":31.86266667,"lon":-96.19747222,"rng_nm":50,"alt_fmsl":0,"id":"PYF","desc":"PYRAMID NDB"}
]
}
